setup.py
zorm/__init__.py
zorm/config.py
zorm/kv.py
zorm/mc.py
zorm/mc_connection.py
zorm/model.py
zorm/query.py
zorm/redis.py
zorm/redis_script.py
zorm/sqlstore.py
zorm.egg-info/PKG-INFO
zorm.egg-info/SOURCES.txt
zorm.egg-info/dependency_links.txt
zorm.egg-info/requires.txt
zorm.egg-info/top_level.txt