Metadata-Version: 1.0
Name: zorm
Version: 0.1331
Summary: A minimal ORM
Home-page: UNKNOWN
Author: zuroc 张沈鹏
Author-email: zsp042@gmail.com
License: UNKNOWN
Platform: UNKNOWN
